gfmodel/__init__.py
gfmodel/core.py
gfmodel-1.0.0.dist-info/METADATA
gfmodel-1.0.0.dist-info/WHEEL
gfmodel-1.0.0.dist-info/top_level.txt
gfmodel-1.0.0.dist-info/RECORD
