Metadata-Version: 2.4
Name: gfmodel
Version: 1.0.0
Summary: Simple Python client for GitHub Models API
Home-page: https://github.com/prakhardoneria/gfmodel
Author: Prakhar Doneria
Author-email: Prakhar Doneria <prakhardoneria3@gmail.com>
License: MIT
Project-URL: Homepage, https://github.com/prakhardoneria/gfmodel
Project-URL: Repository, https://github.com/prakhardoneria/gfmodel
Keywords: github,llm,api,openai,ai
Requires-Python: >=3.8
Requires-Dist: requests>=2.31.0
Dynamic: home-page
Dynamic: requires-python
